Sequential_circuits/Flip-Flop/JK_ff/src/JK_ff.v
module JK_ff(
		output reg Q,
		output q,
		input J,K,clk
);
assign q=~Q;
always@(negedge clk)
	case ({J,K})
		2'b00:Q<=Q;
		2'b01:Q<=0;
		2'b10:Q<=1;
		2'b11:Q<=~Q;
	endcase
endmodule

Synchronous_circuits/Flip-Flop/JK_ff/src/tb_JK_ff.v
`timescale 1ns/1ns
module tb_JK_ff;
reg J,K,clk;//申明输入信号
wire Q,q;//申明输出信号
initial 
	begin
	$display("start a clock pulse");
    $dumpfile("tb_JK_ff.vcd");
    $dumpvars(0,tb_JK_ff);
clk=1;J=1;K=1;//输入信号的波形
#10
clk=1;J=1;K=0;
#2
clk=0;J=1;K=0;
#2
clk=1;J=1;K=1;
#6
clk=1;J=1;K=1;
#10
clk=0;J=0;K=1;
#10
clk=0;J=0;K=1;
#2
clk=1;J=1;K=1;
#2
clk=1;J=1;K=1;
#6
clk=0;J=1;K=1;
#2
clk=1;J=1;K=0;
#2
clk=1;J=1;K=1;
#6
$stop;
$finish;
    end
    JK_ff U1(.J(J),.K(K),.clk(clk),.Q(Q),.q(q));
endmodule

Synchronous sequential circuits/Flip-Flop/JK_ff/tb_JK_ff.vcd
$date
	Tue May 11 10:51:02 2021
$end
$version
	Icarus Verilog
$end
$timescale
	1ns
$end
$scope module tb_JK_ff $end
$var wire 1 ! q $end
$var wire 1 " Q $end
$var reg 1 # J $end
$var reg 1 $ K $end
$var reg 1 % clk $end
$scope module U1 $end
$var wire 1 # J $end
$var wire 1 $ K $end
$var wire 1 % clk $end
$var wire 1 ! q $end
$var reg 1 " Q $end
$upscope $end
$upscope $end
$enddefinitions $end
#0
$dumpvars
1%
1$
1#
x"
x!
$end
#10
0$
#12
0!
1"
0%
#14
1$
1%
#30
1!
0"
0#
0%
#42
1#
1%
#50
0!
1"
0%
#52
0$
1%
#54
1$
