Synchronous sequential circuits/Signal_creater/src/signal_creater3.v
module signal_creater_3 (
    input clk,rst,
    output out
);
reg [3:0]count;
reg out;
initial begin
    count<=3'b000;
end
   always @(posedge clk) begin
    if (~rst) begin
        count<=3'b000;
    end else begin
        if (count==3'b101) begin
            count<=3'b000;
        end else begin
            count<=count+1;
        end
    end
   end 
   always @(count) begin
        case (count)
            3'b000:out=1;
            3'b001:out=0;
            3'b010:out=0;
            3'b011:out=1;
            3'b100:out=1;
            3'b101:out=1; 
            default: out=0;
        endcase
   end
endmodule

Synchronous sequential circuits/Signal_creater/src/tb_signal_creater3.v
`timescale 1ns/1ns
module tb_signal_creater3;
reg clk,rst;//申明输入信号
wire out;//申明输出信号
initial 
	begin
	$display("start a clock pulse");
    $dumpfile("tb_signal_creater3.vcd");
    $dumpvars(0,tb_signal_creater3);
clk=0;rst=0;//输入信号的波形
#10
clk=1;rst=0;
#10
clk=0;rst=1;
#10
clk=1;rst=1;
#10
clk=0;rst=1;
#10
clk=1;rst=1;
#10
clk=0;rst=1;
#10
clk=1;rst=1;
#10
clk=0;rst=1;
#10
clk=1;rst=1;
#10
clk=0;rst=1;
#10
clk=1;rst=1;
#10
clk=0;rst=1;
#10
clk=1;rst=1;
#10
clk=0;rst=1;
#10
clk=1;rst=1;
#10
clk=0;rst=1;
#10
clk=1;rst=1;
#10
clk=0;rst=1;
#10
clk=1;rst=1;
#10
clk=0;rst=1;
#10
clk=1;rst=1;
#10
clk=0;rst=1;
#10
clk=1;rst=1;
#10
clk=0;rst=1;
#10
clk=1;rst=1;
#10
clk=0;rst=1;
#10
clk=1;rst=1;
#10
clk=0;rst=1;
#10
clk=1;rst=1;
#10
clk=0;rst=1;
#10
clk=1;rst=1;
#10
clk=0;rst=1;
#10
clk=1;rst=1;
#10
clk=0;rst=1;
#10
clk=1;rst=1;
#10
$stop;
$finish;
		end
signal_creater_3 U1(.clk(clk),.rst(rst),.out(out));
endmodule

Synchronous sequential circuits/Signal_creater/tb_signal_creater3.vcd
$date
	Tue May 18 16:42:36 2021
$end
$version
	Icarus Verilog
$end
$timescale
	1ns
$end
$scope module tb_signal_creater3 $end
$var wire 1 ! out $end
$var reg 1 " clk $end
$var reg 1 # rst $end
$scope module U1 $end
$var wire 1 " clk $end
$var wire 1 # rst $end
$var reg 4 $ count [3:0] $end
$var reg 1 ! out $end
$upscope $end
$upscope $end
$enddefinitions $end
#0
$dumpvars
b0 $
0#
0"
1!
$end
#10
1"
#20
1#
0"
#30
0!
b1 $
1"
#40
0"
#50
b10 $
1"
#60
0"
#70
1!
b11 $
1"
#80
0"
#90
b100 $
1"
#100
0"
#110
b101 $
1"
#120
0"
#130
b0 $
1"
#140
0"
#150
0!
b1 $
1"
#160
0"
#170
b10 $
1"
#180
0"
#190
1!
b11 $
1"
#200
0"
#210
b100 $
1"
#220
0"
#230
b101 $
1"
#240
0"
#250
b0 $
1"
#260
0"
#270
0!
b1 $
1"
#280
0"
#290
b10 $
1"
#300
0"
#310
1!
b11 $
1"
#320
0"
#330
b100 $
1"
#340
0"
#350
b101 $
1"
