Synchronous sequential circuits/Flip-Flop/Twofour_divider/src/2_4divider.v
module two_divider(
    input cp,rst,
    output reg Q0,
    output q
);//行为级建模
    always @(posedge cp or negedge rst) begin
        if (!rst) begin
            Q0<=0;
        end else begin
             Q0<=~Q0;
        end
    end
    assign q=~Q0;
endmodule
module two_four_divider (
    output Q0,Q1,
    input cp,rst
);
wire w1;
    two_divider U1(.cp(cp),.rst(rst),.Q0(Q0),.q(w1));
    two_divider U2(.cp(w1),.rst(rst),.Q0(Q1),.q());
endmodule

Synchronous sequential circuits/Flip-Flop/Twofour_divider/src/tb_two_divide.v
`timescale 1ns/1ns
module tb_two_divide;
reg cp,rst;//申明输入信号
wire Q1,Q0;//申明输出信号
initial 
	begin
	$display("start a clock pulse");
    $dumpfile("tb_two_divide.vcd");
    $dumpvars(0,tb_two_divide);
cp=0;rst=0;//输入信号的波形
#10
cp=1;rst=0;
#10
cp=0;rst=0;//输入信号的波形
#10
cp=1;rst=1;
#10
cp=0;rst=1;
#10
cp=1;rst=1;
#10
cp=0;rst=1;
#10
cp=1;rst=1;
#10
cp=0;rst=1;
#10
cp=1;rst=1;
#10
cp=0;rst=0;
#10
cp=1;rst=0;
#10
cp=0;rst=0;
#10
cp=1;rst=0;
#10
cp=0;rst=0;
#10
cp=1;rst=0;
#10
$stop;
$finish;
    end
    two_four_divider U1(.cp(cp),.rst(rst),.Q1(Q1),.Q0(Q0));
endmodule

Synchronous sequential circuits/Flip-Flop/Twofour_divider/tb_two_divide.vcd
$date
	Mon May 17 18:05:21 2021
$end
$version
	Icarus Verilog
$end
$timescale
	1ns
$end
$scope module tb_two_divide $end
$var wire 1 ! Q1 $end
$var wire 1 " Q0 $end
$var reg 1 # cp $end
$var reg 1 $ rst $end
$scope module U1 $end
$var wire 1 # cp $end
$var wire 1 $ rst $end
$var wire 1 % w1 $end
$var wire 1 ! Q1 $end
$var wire 1 " Q0 $end
$scope module U1 $end
$var wire 1 # cp $end
$var wire 1 % q $end
$var wire 1 $ rst $end
$var reg 1 " Q0 $end
$upscope $end
$scope module U2 $end
$var wire 1 % cp $end
$var wire 1 & q $end
$var wire 1 $ rst $end
$var reg 1 ! Q0 $end
$upscope $end
$upscope $end
$upscope $end
$enddefinitions $end
#0
$dumpvars
1&
1%
0$
0#
0"
0!
$end
#10
1#
#20
0#
#30
0%
1"
1$
1#
#40
0#
#50
0&
1!
1%
0"
1#
#60
0#
#70
0%
1"
1#
#80
0#
#90
1&
0!
1%
0"
1#
#100
0$
0#
#110
1#
#120
0#
#130
1#
#140
0#
#150
1#
