System_design/FIFO/src/ram_2_module.v
module ram_module (
	input[7:0]data_in,
	input [2:0]write_addr,read_addr,
	input wr,rd,
	input clk1,clk2,
	output reg[7:0]data_out
);
	reg [7:0]mem[7:0];
	always @(posedge clk1) begin
		if (wr) begin
			mem[write_addr]<=data_in;
		end else begin
			
		end
	end
	always @(posedge clk2 ) begin
		if (rd) begin
			data_out<=mem[read_addr];
		end else begin
			
		end
	end
endmodule

System_design/FIFO/src/control_modulefixed.v
module control_module
#(
	parameter  DATA_WIDTH =  8,
	parameter  DATA_DEPTH =  8,
	parameter  RAM_DEPTH  =  (1 << DATA_DEPTH)
)
(
	input      							clk,
	input      							rst_n,
	input  	  [DATA_WIDTH-1:0]   data_in,
	input      							write_signal,
	input      							read_signal,
	output  reg   				[2:0]  write_addr,read_addr,data_addr,
	output 								fall,empty
);

	assign fall=(data_addr==DATA_DEPTH-1)?1'b1:1'b0;
	assign empty=(data_addr==1'b0)?1'b1:1'b0;
//-------------------------------------------------------
	always @(posedge clk or negedge rst_n)begin
		if(rst_n == 1'b0)begin
			write_addr <= 0;
		end
		else if(write_addr == RAM_DEPTH-1)
			write_addr <= 0;
		else if(write_signal)begin
			write_addr <= write_addr + 1'b1;
		end
		else
			write_addr <= write_addr;
	end

//-------------------------------------------------------
	always @(posedge clk or negedge rst_n)begin
		if(rst_n == 1'b0)begin
			read_addr <= 0;
		end
		else if(read_addr == RAM_DEPTH-1)
			read_addr <= 0;
		else if(read_signal)begin
			read_addr <= read_addr + 1'b1;
		end
		else
			read_addr <= read_addr;
	end
///-------------------------------------------------------
	always @(posedge clk or negedge rst_n) begin
		if (rst_n==1'b0) begin
			data_addr=0;
		end 
		else if (read_signal&&!write_signal&&data_addr!=0) begin
			data_addr<=data_addr-1;
		end
		else if (!read_signal&&write_signal&&data_addr!=DATA_DEPTH-1) begin
			data_addr<=data_addr+1;
		end
		else begin
			data_addr<=data_addr;
		end
	end
endmodule

System_design/FIFO/src/fifo_top.v
module fifo_top (
	input write_signal,read_signal,clk,rst_n,
	input [7:0] data_in,
	output [7:0] data_out
);
wire [2:0]write_addr,read_addr;
wire fall,empty;
	control_module C1(.write_signal(write_signal),.read_signal(read_signal),.clk(clk),.rst_n(rst_n),.write_addr(write_addr),.read_addr(read_addr),.fall(fall),.empty(empty));
	ram_module R2(.write_addr(write_addr),.read_addr(read_addr),.data_in(data_in),.data_out(data_out),.clk1(clk),.clk2(clk),.wr(write_signal),.rd(read_signal));
endmodule

System_design/FIFO/src/tb_fifo_top.v
`timescale 1ns/1ns
module tb_fifo_top;
reg write_signal,read_signal,clk,rst_n;
reg [7:0] data_in;//申明输入信号
wire [7:0] data_out;//申明输出信号
fifo_top U1(.write_signal(write_signal),.read_signal(read_signal),.clk(clk),.rst_n(rst_n),.data_in(data_in),.data_out(data_out));//调用模块实例化
initial 
	begin
	$display("start a clock pulse");
    	$dumpfile("tb_fifo_top.vcd");
    	$dumpvars(0,tb_fifo_top);
	end
initial begin
	clk=0;rst_n=1;data_in=0;
	write_signal=1;read_signal=0;
	#5 rst_n=0;
	#1 rst_n=1;
	#155 write_signal=0;
		 read_signal=1;
end	
initial begin
	repeat(40)
	#10clk=!clk;
end
initial begin
	repeat(7)
	#20 data_in=data_in+1;
end
endmodule

System_design/FIFO/tb_fifo_top.vcd
$date
	Fri Jun 11 15:15:33 2021
$end
$version
	Icarus Verilog
$end
$timescale
	1ns
$end
$scope module tb_fifo_top $end
$var wire 8 ! data_out [7:0] $end
$var reg 1 " clk $end
$var reg 8 # data_in [7:0] $end
$var reg 1 $ read_signal $end
$var reg 1 % rst_n $end
$var reg 1 & write_signal $end
$scope module U1 $end
$var wire 1 " clk $end
$var wire 8 ' data_in [7:0] $end
$var wire 1 $ read_signal $end
$var wire 1 % rst_n $end
$var wire 1 & write_signal $end
$var wire 3 ( write_addr [2:0] $end
$var wire 3 ) read_addr [2:0] $end
$var wire 1 * fall $end
$var wire 1 + empty $end
$var wire 8 , data_out [7:0] $end
$scope module C1 $end
$var wire 1 " clk $end
$var wire 8 - data_in [7:0] $end
$var wire 1 $ read_signal $end
$var wire 1 % rst_n $end
$var wire 1 & write_signal $end
$var wire 1 * fall $end
$var wire 1 + empty $end
$var reg 3 . data_addr [2:0] $end
$var reg 3 / read_addr [2:0] $end
$var reg 3 0 write_addr [2:0] $end
$upscope $end
$scope module R2 $end
$var wire 1 " clk1 $end
$var wire 1 " clk2 $end
$var wire 8 1 data_in [7:0] $end
$var wire 1 $ rd $end
$var wire 3 2 read_addr [2:0] $end
$var wire 1 & wr $end
$var wire 3 3 write_addr [2:0] $end
$var reg 8 4 data_out [7:0] $end
$upscope $end
$upscope $end
$upscope $end
$enddefinitions $end
#0
$dumpvars
bx 4
bx 3
bx 2
b0 1
bx 0
bx /
bx .
bz -
bx ,
x+
x*
bx )
bx (
b0 '
1&
1%
0$
b0 #
0"
bx !
$end
#5
b0 (
b0 0
b0 3
b0 )
b0 /
b0 2
0*
1+
b0 .
0%
#6
1%
#10
0+
b1 .
b1 (
b1 0
b1 3
1"
#20
0"
b1 #
b1 '
b1 1
#30
b10 (
b10 0
b10 3
b10 .
1"
#40
0"
b10 #
b10 '
b10 1
#50
b11 .
b11 (
b11 0
b11 3
1"
#60
0"
b11 #
b11 '
b11 1
#70
b100 (
b100 0
b100 3
b100 .
1"
#80
0"
b100 #
b100 '
b100 1
#90
b101 .
b101 (
b101 0
b101 3
1"
#100
0"
b101 #
b101 '
b101 1
#110
b110 (
b110 0
b110 3
b110 .
1"
#120
0"
b110 #
b110 '
b110 1
#130
1*
b111 .
b111 (
b111 0
b111 3
1"
#140
0"
b111 #
b111 '
b111 1
#150
b0 (
b0 0
b0 3
1"
#160
0"
#161
1$
0&
#170
0*
b110 .
b1 )
b1 /
b1 2
b0 !
b0 ,
b0 4
1"
#180
0"
#190
b10 )
b10 /
b10 2
b101 .
b1 !
b1 ,
b1 4
1"
#200
0"
#210
b100 .
b11 )
b11 /
b11 2
b10 !
b10 ,
b10 4
1"
#220
0"
#230
b100 )
b100 /
b100 2
b11 .
b11 !
b11 ,
b11 4
1"
#240
0"
#250
b10 .
b101 )
b101 /
b101 2
b100 !
b100 ,
b100 4
1"
#260
0"
#270
b110 )
b110 /
b110 2
b1 .
b101 !
b101 ,
b101 4
1"
#280
0"
#290
1+
b0 .
b111 )
b111 /
b111 2
b110 !
b110 ,
b110 4
1"
#300
0"
#310
b0 )
b0 /
b0 2
b111 !
b111 ,
b111 4
1"
#320
0"
#330
b1 )
b1 /
b1 2
b0 !
b0 ,
b0 4
1"
#340
0"
#350
b10 )
b10 /
b10 2
b1 !
b1 ,
b1 4
1"
#360
0"
#370
b11 )
b11 /
b11 2
b10 !
b10 ,
b10 4
1"
#380
0"
#390
b100 )
b100 /
b100 2
b11 !
b11 ,
b11 4
1"
