Summer_campus/CPU_ISA&Microarc/homework/src/DFF.v
module DFF #(
	parameter DATA_SIZE = 8
) (
	input [DATA_SIZE-1:0]D,
	input CLK,RESET_n,LD,
	output reg[DATA_SIZE-1:0]Q
);
	always @(posedge CLK or negedge RESET_n) begin
		if(!RESET_n) begin
			Q <= 0;
		end
		else begin
		  if (LD) begin
			  Q<=D;
		  end else begin
			  Q<=Q;
		  end
		end
	end
endmodule

Summer_campus/CPU_ISA&Microarc/homework/src/ram_1.v
module ram_1 #(
	parameter DATA_SIZE = 8,
	parameter DATA_DEPTH = 3
)
(
	input clk,wr_,cs_,
	input [DATA_DEPTH-1:0]addr,
	input [DATA_SIZE-1:0] data_in,
	output reg [DATA_SIZE-1:0] data_out


);
	reg [DATA_SIZE-1:0] ram [0:DATA_DEPTH-1];
	always @(posedge clk) begin
			if (!wr_) begin
				ram[addr] <= data_in;
			end else begin
				data_out <=ram[addr];
			end
		end
endmodule

Summer_campus/homework_fixed/src/counter.v
module counter (
	input CLK,Reset_n,
	output reg[1:0]addr
);
	always @(posedge CLK or negedge Reset_n) begin
		if (!Reset_n) begin
			addr=2'b00;
		end else begin
			if (addr==2'b10) begin
				addr<=2'b00;
			end else begin
				addr<=addr+1'b1;
			end
		end
	end
endmodule

Summer_campus/CPU_ISA&Microarc/homework/src/control.v
module control (
	input Valid_i,Ready_i,
	input [7:0]Data_o,
	output Valid_o,Ready_o,
	output [2:0] LD
);
	assign Valid_o=(Data_o>8'b00_000_000)?1'b1:1'b0;
	assign  Ready_o=Ready_i;
	assign LD=(Valid_i)?3'b111:3'b000;
endmodule

Summer_campus/CPU_ISA&Microarc/homework/src/Flow_Control_Flow_top.v
`include "/Users/alexieshe/Desktop/MyDigitalworks/My_Digitalworks/Summer_campus/CPU_ISA&Microarc/homework/src/control.v"
`include "/Users/alexieshe/Desktop/MyDigitalworks/My_Digitalworks/Summer_campus/CPU_ISA&Microarc/homework/src/DFF.v"
`include "/Users/alexieshe/Desktop/MyDigitalworks/My_Digitalworks/Summer_campus/CPU_ISA&Microarc/homework/src/counter.v"
`include "/Users/alexieshe/Desktop/MyDigitalworks/My_Digitalworks/Summer_campus/CPU_ISA&Microarc/homework/src/ram_1.v"
module Flow_Control_Flow (
	input Valid_i,Ready_i,CLK,RESET_n,
	input [7:0]Data_i,
	output [7:0]Data_o,
	output Ready_o,Valid_o
);
	wire [2:0] LD;
	wire [1:0] addr;
	wire [7:0] Q1,Q2,Q3;
	wire [7:0] Data_o_DFF,Data_o_ram;
	assign Data_o_DFF=Q3;

	control c1(.Valid_i(Valid_i),.Ready_i(Ready_i),.Valid_o(Valid_o),.Ready_o(Ready_o),.LD(LD),.Data_o(Q3));
	counter count(.CLK(CLK),.addr(addr),.Reset_n(RESET_n));
	ram_1 #(8,2)ram(.clk(CLK),.wr_(Ready_i),.addr(addr),.data_in(Data_o_DFF),.data_out(Data_o_ram));
	DFF#(8) D0(.D(Data_i),.CLK(CLK),.RESET_n(RESET_n),.LD(LD[0]),.Q(Q1));
	DFF#(8) D1(.D(Q1),.CLK(CLK),.RESET_n(RESET_n),.LD(LD[1]),.Q(Q2));
	DFF#(8) D2(.D(Q2),.CLK(CLK),.RESET_n(RESET_n),.LD(LD[2]),.Q(Q3));

endmodule

Summer_campus/CPU_ISA&Microarc/homework/src/tb_FLow_Control.v
`timescale 1ns/1ns
module tb_Flow_Control_Flow;
parameter DATA_SIZE = 8;
reg Valid_i,Ready_i,CLK,RESET_n;//申明输入信号
reg [7:0] Data_i;
wire [7:0]Data_o;
wire Ready_o;//申明输出信
Flow_Control_Flow F1(.Valid_i(Valid_i),.Ready_i(Ready_i),.Valid_o(Valid_o),.Ready_o(Ready_o),.Data_i(Data_i),.CLK(CLK),.RESET_n(RESET_n),.Data_o(Data_o));
initial begin
$dumpvars (0,tb_Flow_Control_Flow);
$dumpfile("tb_Flow_Control_Flow.vcd");
end
initial begin
 CLK=0;
 RESET_n=0;
#10 RESET_n=1;
end
always #10 CLK=~CLK;
always #20 Data_i={$random}%(1<<DATA_SIZE);
initial begin

#10 Valid_i=0;Ready_i=0;
#10 Valid_i=0;Ready_i=1;
#10 Valid_i=1;Ready_i=0;
#10 Valid_i=1;Ready_i=1;
#100 Valid_i=1;Ready_i=0;
#60 Valid_i=1;Ready_i=1;
#100
$stop;
$finish;
end
endmodule

Summer_campus/CPU_ISA&Microarc/homework/dump.vcd
$date
	Mon Jul 26 07:23:46 2021
$end
$version
	Icarus Verilog
$end
$timescale
	1ns
$end
$scope module tb_Flow_Control_Flow $end
$var wire 8 ! Data_o [7:0] $end
$var wire 1 " Valid_o $end
$var wire 1 # Ready_o $end
$var reg 1 $ CLK $end
$var reg 8 % Data_i [7:0] $end
$var reg 1 & RESET_n $end
$var reg 1 ' Ready_i $end
$var reg 1 ( Valid_i $end
$scope module F1 $end
$var wire 1 $ CLK $end
$var wire 8 ) Data_i [7:0] $end
$var wire 8 * Data_o [7:0] $end
$var wire 8 + Data_o_DFF [7:0] $end
$var wire 1 & RESET_n $end
$var wire 1 ' Ready_i $end
$var wire 1 ( Valid_i $end
$var wire 2 , addr [1:0] $end
$var wire 1 " Valid_o $end
$var wire 1 # Ready_o $end
$var wire 8 - Q3 [7:0] $end
$var wire 8 . Q2 [7:0] $end
$var wire 8 / Q1 [7:0] $end
$var wire 3 0 LD [2:0] $end
$var wire 8 1 Data_o_ram [7:0] $end
$scope module D0 $end
$var wire 1 $ CLK $end
$var wire 8 2 D [7:0] $end
$var wire 1 3 LD $end
$var wire 1 & RESET_n $end
$var reg 8 4 Q [7:0] $end
$upscope $end
$scope module D1 $end
$var wire 1 $ CLK $end
$var wire 8 5 D [7:0] $end
$var wire 1 6 LD $end
$var wire 1 & RESET_n $end
$var reg 8 7 Q [7:0] $end
$upscope $end
$scope module D2 $end
$var wire 1 $ CLK $end
$var wire 8 8 D [7:0] $end
$var wire 1 9 LD $end
$var wire 1 & RESET_n $end
$var reg 8 : Q [7:0] $end
$upscope $end
$scope module c1 $end
$var wire 8 ; Data_o [7:0] $end
$var wire 1 ' Ready_i $end
$var wire 1 # Ready_o $end
$var wire 1 ( Valid_i $end
$var wire 1 " Valid_o $end
$var wire 3 < LD [2:0] $end
$upscope $end
$scope module count $end
$var wire 1 $ CLK $end
$var wire 1 & Reset_n $end
$var reg 2 = addr [1:0] $end
$upscope $end
$scope module ram $end
$var wire 2 > addr [1:0] $end
$var wire 1 $ clk $end
$var wire 8 ? data_in [7:0] $end
$var wire 1 ' wr_ $end
$var reg 8 @ data_out [7:0] $end
$upscope $end
$upscope $end
$upscope $end
$enddefinitions $end
#0
$dumpvars
bx @
b0 ?
b0 >
b0 =
bx <
b0 ;
b0 :
x9
b0 8
b0 7
x6
b0 5
b0 4
x3
bx 2
bx 1
bx 0
b0 /
b0 .
b0 -
b0 ,
b0 +
bz *
bx )
x(
x'
0&
bx %
0$
x#
0"
bz !
$end
#10
b1 ,
b1 =
b1 >
09
06
03
b0 0
b0 <
0#
0'
0(
1$
1&
#20
1#
1'
0$
b100100 %
b100100 )
b100100 2
#30
b10 ,
b10 =
b10 >
19
16
13
b111 0
b111 <
0#
0'
1(
1$
#40
1#
1'
0$
b10000001 %
b10000001 )
b10000001 2
#50
b10000001 /
b10000001 4
b10000001 5
b0 ,
b0 =
b0 >
1$
#60
0$
b1001 %
b1001 )
b1001 2
#70
b1 ,
b1 =
b1 >
b1001 /
b1001 4
b1001 5
b10000001 .
b10000001 7
b10000001 8
b0 1
b0 @
1$
#80
0$
b1100011 %
b1100011 )
b1100011 2
#90
1"
b10000001 +
b10000001 ?
b10000001 -
b10000001 :
b10000001 ;
b1001 .
b1001 7
b1001 8
b1100011 /
b1100011 4
b1100011 5
b10 ,
b10 =
b10 >
1$
#100
0$
b1101 %
b1101 )
b1101 2
#110
b0 ,
b0 =
b0 >
b1101 /
b1101 4
b1101 5
b1100011 .
b1100011 7
b1100011 8
b1001 +
b1001 ?
b1001 -
b1001 :
b1001 ;
bx 1
bx @
1$
#120
0$
b10001101 %
b10001101 )
b10001101 2
#130
b1100011 +
b1100011 ?
b1100011 -
b1100011 :
b1100011 ;
b1101 .
b1101 7
b1101 8
b10001101 /
b10001101 4
b10001101 5
b1 ,
b1 =
b1 >
b0 1
b0 @
1$
#140
0$
b1100101 %
b1100101 )
b1100101 2
0#
0'
#150
b10 ,
b10 =
b10 >
b1100101 /
b1100101 4
b1100101 5
b10001101 .
b10001101 7
b10001101 8
b1101 +
b1101 ?
b1101 -
b1101 :
b1101 ;
1$
#160
0$
b10010 %
b10010 )
b10010 2
#170
b10001101 +
b10001101 ?
b10001101 -
b10001101 :
b10001101 ;
b1100101 .
b1100101 7
b1100101 8
b10010 /
b10010 4
b10010 5
b0 ,
b0 =
b0 >
1$
#180
0$
b1 %
b1 )
b1 2
#190
b1 ,
b1 =
b1 >
b1 /
b1 4
b1 5
b10010 .
b10010 7
b10010 8
b1100101 +
b1100101 ?
b1100101 -
b1100101 :
b1100101 ;
1$
#200
0$
b1101 %
b1101 )
b1101 2
1#
1'
#210
b10010 +
b10010 ?
b10010 -
b10010 :
b10010 ;
b1 .
b1 7
b1 8
b1101 /
b1101 4
b1101 5
b10 ,
b10 =
b10 >
b1100011 1
b1100011 @
1$
#220
0$
b1110110 %
b1110110 )
b1110110 2
#230
b0 ,
b0 =
b0 >
b1110110 /
b1110110 4
b1110110 5
b1101 .
b1101 7
b1101 8
b1 +
b1 ?
b1 -
b1 :
b1 ;
bx 1
bx @
1$
#240
0$
b111101 %
b111101 )
b111101 2
#250
b1101 +
b1101 ?
b1101 -
b1101 :
b1101 ;
b1110110 .
b1110110 7
b1110110 8
b111101 /
b111101 4
b111101 5
b1 ,
b1 =
b1 >
b10001101 1
b10001101 @
1$
#260
0$
b11101101 %
b11101101 )
b11101101 2
#270
b10 ,
b10 =
b10 >
b11101101 /
b11101101 4
b11101101 5
b111101 .
b111101 7
b111101 8
b1110110 +
b1110110 ?
b1110110 -
b1110110 :
b1110110 ;
b1100011 1
b1100011 @
1$
#280
0$
b10001100 %
b10001100 )
b10001100 2
#290
b111101 +
b111101 ?
b111101 -
b111101 :
b111101 ;
b11101101 .
b11101101 7
b11101101 8
b10001100 /
b10001100 4
b10001100 5
b0 ,
b0 =
b0 >
bx 1
bx @
1$
